AUTHORS
Changelog
FAQ
INSTALL
LICENSE
MANIFEST.in
README
README.rst
THANKS
setup.cfg
setup.py
django_zcelery.egg-info/PKG-INFO
django_zcelery.egg-info/SOURCES.txt
django_zcelery.egg-info/dependency_links.txt
django_zcelery.egg-info/not-zip-safe
django_zcelery.egg-info/requires.txt
django_zcelery.egg-info/top_level.txt
djcelery/__init__.py
djcelery/admin.py
djcelery/admin_utils.py
djcelery/app.py
djcelery/apps.py
djcelery/common.py
djcelery/compat.py
djcelery/db.py
djcelery/humanize.py
djcelery/loaders.py
djcelery/managers.py
djcelery/models.py
djcelery/mon.py
djcelery/picklefield.py
djcelery/schedulers.py
djcelery/snapshot.py
djcelery/urls.py
djcelery/utils.py
djcelery/views.py
djcelery/backends/__init__.py
djcelery/backends/cache.py
djcelery/backends/database.py
djcelery/contrib/__init__.py
djcelery/contrib/test_runner.py
djcelery/locale/en/LC_MESSAGES/django.po
djcelery/locale/es/LC_MESSAGES/django.mo
djcelery/locale/es/LC_MESSAGES/django.po
djcelery/locale/zh_Hans/LC_MESSAGES/django.mo
djcelery/locale/zh_Hans/LC_MESSAGES/django.po
djcelery/management/__init__.py
djcelery/management/base.py
djcelery/management/commands/__init__.py
djcelery/management/commands/celery.py
djcelery/management/commands/celerybeat.py
djcelery/management/commands/celerycam.py
djcelery/management/commands/celeryd.py
djcelery/management/commands/celeryd_detach.py
djcelery/management/commands/celeryd_multi.py
djcelery/management/commands/celerymon.py
djcelery/management/commands/djcelerymon.py
djcelery/migrations/0001_initial.py
djcelery/migrations/__init__.py
djcelery/monproj/__init__.py
djcelery/monproj/urls.py
djcelery/static/djcelery/style.css
djcelery/templates/admin/djcelery/change_list.html
djcelery/templates/djcelery/confirm_rate_limit.html
djcelery/tests/__init__.py
djcelery/tests/_compat.py
djcelery/tests/req.py
djcelery/tests/test_commands.py
djcelery/tests/test_discovery.py
djcelery/tests/test_loaders.py
djcelery/tests/test_models.py
djcelery/tests/test_schedulers.py
djcelery/tests/test_snapshot.py
djcelery/tests/test_views.py
djcelery/tests/test_worker_job.py
djcelery/tests/utils.py
djcelery/tests/test_backends/__init__.py
djcelery/tests/test_backends/test_cache.py
